MANIFEST.in
requirements-test.txt
requirements.txt
setup.py
stdeb.cfg
debian/changelog
debian/compat
debian/control
debian/python-upaas-common.preinst
debian/rules
debian/source/format
tests/__init__.py
tests/conftest.py
tests/test_commands.py
tests/test_config.py
tests/test_storage_local.py
tests/test_storage_mongodb.py
upaas/__init__.py
upaas/checksum.py
upaas/chroot.py
upaas/client.py
upaas/commands.py
upaas/compat.py
upaas/distro.py
upaas/inet.py
upaas/processes.py
upaas/tar.py
upaas/utils.py
upaas/builder/__init__.py
upaas/builder/builder.py
upaas/builder/exceptions.py
upaas/cli/__init__.py
upaas/cli/base.py
upaas/config/__init__.py
upaas/config/base.py
upaas/config/metadata.py
upaas/storage/__init__.py
upaas/storage/base.py
upaas/storage/exceptions.py
upaas/storage/local.py
upaas/storage/mongodb.py
upaas/storage/utils.py
upaas_common.egg-info/PKG-INFO
upaas_common.egg-info/SOURCES.txt
upaas_common.egg-info/dependency_links.txt
upaas_common.egg-info/requires.txt
upaas_common.egg-info/top_level.txt