Metadata-Version: 1.1
Name: upaas-common
Version: 0.2.1
Summary: uPaaS common classes
Home-page: https://github.com/prymitive/upaas-common
Author: Łukasz Mierzwa
Author-email: l.mierzwa@gmail.com
License: GPLv3
Platform: Linux
Classifier: License :: OSI Approved :: GNU General Public License v3 (GPLv3)
Classifier: Intended Audience :: Developers
Classifier: Intended Audience :: System Administrators
Classifier: Programming Language :: Python
Classifier: Topic :: Software Development :: Libraries :: Python Modules
